rufmich/__init__.py
rufmich/error.py
rufmich/request.py
rufmich/response.py
rufmich/server.py
rufmich-1.0.6.dist-info/LICENSE
rufmich-1.0.6.dist-info/METADATA
rufmich-1.0.6.dist-info/WHEEL
rufmich-1.0.6.dist-info/top_level.txt
rufmich-1.0.6.dist-info/RECORD
