Metadata-Version: 2.1
Name: rufmich
Version: 1.0.6
Summary: A Python server implementaion of JSON-RPC 2.0 over HTTP
Home-page: https://github.com/daseinpwt/rufmich
Author: daseinpwt
Author-email: daseinpwt@gmail.com
License: UNKNOWN
Platform: UNKNOWN
Classifier: Programming Language :: Python :: 3
Classifier: Operating System :: OS Independent
Requires-Dist: flask
